rustileo-0.1.0.dist-info/METADATA
rustileo-0.1.0.dist-info/WHEEL
rustileo-0.1.0.dist-info/licenses/LICENSE
rustileo/__init__.py
rustileo/rustileo.cpython-312-darwin.so
rustileo-0.1.0.dist-info/RECORD
