Metadata-Version: 2.4
Name: rustileo
Version: 0.1.0
Classifier: Programming Language :: Rust
Classifier: Programming Language :: Python :: Implementation :: CPython
Classifier: Programming Language :: Python :: Implementation :: PyPy
Requires-Dist: maturin >=1.8.1
Requires-Dist: pip >=24.3.1
Requires-Dist: pytest >=8.3.4
Requires-Dist: ruff >=0.9.2
License-File: LICENSE
Author: Vasco Schiavo <vasco.schiavo@protonmail.com>
Author-email: Vasco Schiavo <vasco.schiavo@protonmail.com>
Requires-Python: >=3.8
